bmx280_spi/__init__.py
bmx280_spi/__main__.py
bmx280_spi-1.0.4.dist-info/LICENSE
bmx280_spi-1.0.4.dist-info/METADATA
bmx280_spi-1.0.4.dist-info/WHEEL
bmx280_spi-1.0.4.dist-info/top_level.txt
bmx280_spi-1.0.4.dist-info/RECORD
