Metadata-Version: 2.1
Name: bmx280-spi
Version: 1.0.4
Summary: Python module to use the SPI bus to read bmp280/bme280 sensors
Author-email: Thomas Dunteman <git@learningtopi.com>
Project-URL: Homepage, https://www.learningtopi.com/python-modules-applications/bmx280_spi/
Project-URL: Bug Tracker, https://github.com/LearningToPi/bmx280_spi/issues
Project-URL: Source Code, https://github.com/LearningToPi/bmx280_spi
Keywords: bmp280,bme280,spi
Classifier: Topic :: System :: Logging
Classifier: License :: OSI Approved :: MIT License
Classifier: Programming Language :: Python :: 3
Classifier: Topic :: Software Development :: Libraries :: Python Modules
Classifier: Topic :: System :: Hardware :: Hardware Drivers
Requires-Python: >=3.6
License-File: LICENSE
Requires-Dist: logging-handler
Requires-Dist: spidev
Requires-Dist: gpiod
